{
    "expires": 1780843744,
    "content": {
        "coord": {
            "lon": 55.94749999999999801048033987171947956085205078125,
            "lat": 54.726100000000002410160959698259830474853515625
        },
        "weather": [
            {
                "id": 500,
                "main": "Rain",
                "description": "небольшой дождь",
                "icon": "10d"
            }
        ],
        "base": "stations",
        "main": {
            "temp": 17.6700000000000017053025658242404460906982421875,
            "feels_like": 17.629999999999999005240169935859739780426025390625,
            "temp_min": 17.6700000000000017053025658242404460906982421875,
            "temp_max": 17.6700000000000017053025658242404460906982421875,
            "pressure": 1013,
            "humidity": 82,
            "sea_level": 1013,
            "grnd_level": 999
        },
        "visibility": 10000,
        "wind": {
            "speed": 2.75,
            "deg": 356,
            "gust": 5.2400000000000002131628207280300557613372802734375
        },
        "rain": {
            "1h": 0.63000000000000000444089209850062616169452667236328125
        },
        "clouds": {
            "all": 29
        },
        "dt": 1780843237,
        "sys": {
            "country": "RU",
            "sunrise": 1780789323,
            "sunset": 1780850895
        },
        "timezone": 18000,
        "id": 488500,
        "name": "Старое Барятино",
        "cod": 200
    }
}